v4_client_py/__init__.py
v4_client_py/chain/__init__.py
v4_client_py/chain/aerial/__init__.py
v4_client_py/chain/aerial/client/__init__.py
v4_client_py/chain/aerial/client/bank.py
v4_client_py/chain/aerial/client/distribution.py
v4_client_py/chain/aerial/client/staking.py
v4_client_py/chain/aerial/client/utils.py
v4_client_py/chain/aerial/coins.py
v4_client_py/chain/aerial/config.py
v4_client_py/chain/aerial/exceptions.py
v4_client_py/chain/aerial/faucet.py
v4_client_py/chain/aerial/gas.py
v4_client_py/chain/aerial/tx.py
v4_client_py/chain/aerial/tx_helpers.py
v4_client_py/chain/aerial/urls.py
v4_client_py/chain/aerial/wallet.py
v4_client_py/chain/auth/__init__.py
v4_client_py/chain/auth/interface.py
v4_client_py/chain/auth/rest_client.py
v4_client_py/chain/bank/__init__.py
v4_client_py/chain/bank/interface.py
v4_client_py/chain/bank/rest_client.py
v4_client_py/chain/common/__init__.py
v4_client_py/chain/common/rest_client.py
v4_client_py/chain/common/types.py
v4_client_py/chain/common/utils.py
v4_client_py/chain/crypto/__init__.py
v4_client_py/chain/crypto/address.py
v4_client_py/chain/crypto/hashfuncs.py
v4_client_py/chain/crypto/interface.py
v4_client_py/chain/crypto/keypairs.py
v4_client_py/chain/crypto/keypairs_bls.py
v4_client_py/chain/distribution/__init__.py
v4_client_py/chain/distribution/interface.py
v4_client_py/chain/distribution/rest_client.py
v4_client_py/chain/evidence/__init__.py
v4_client_py/chain/evidence/interface.py
v4_client_py/chain/evidence/rest_client.py
v4_client_py/chain/gov/__init__.py
v4_client_py/chain/gov/interface.py
v4_client_py/chain/gov/rest_client.py
v4_client_py/chain/mint/__init__.py
v4_client_py/chain/mint/interface.py
v4_client_py/chain/mint/rest_client.py
v4_client_py/chain/params/__init__.py
v4_client_py/chain/params/interface.py
v4_client_py/chain/params/rest_client.py
v4_client_py/chain/slashing/__init__.py
v4_client_py/chain/slashing/interface.py
v4_client_py/chain/slashing/rest_client.py
v4_client_py-4.0.0.dist-info/LICENSE
v4_client_py-4.0.0.dist-info/METADATA
v4_client_py-4.0.0.dist-info/WHEEL
v4_client_py-4.0.0.dist-info/RECORD
